dircomply/__init__.py
dircomply/compare.py
dircomply/gui.py
dircomply/help.py
dircomply/main.py
dircomply/read.py
dircomply/utils.py
dircomply/version.py
dircomply/config/__init__.py
dircomply/config/config.py
dircomply/config/extensions.json
dircomply-1.0.0.dist-info/licenses/LICENSE
dircomply-1.0.0.dist-info/METADATA
dircomply-1.0.0.dist-info/WHEEL
dircomply-1.0.0.dist-info/entry_points.txt
dircomply-1.0.0.dist-info/top_level.txt
dircomply-1.0.0.dist-info/RECORD
